pymvola/__init__.py
pymvola/core.py
pymvola/exceptions.py
pymvola/models.py
pymvola/util/__init__.py
pymvola/util/authorization.py
pymvola/util/consts.py
pymvola/util/date_.py
pymvola/util/enumeration.py
pymvola/util/uuid_.py
pymvola-0.1.1.dist-info/METADATA
pymvola-0.1.1.dist-info/WHEEL
pymvola-0.1.1.dist-info/licenses/LICENSE
pymvola-0.1.1.dist-info/RECORD
