Metadata-Version: 2.1
Name: pymvola
Version: 0.1.1
Summary: Open source and easy use of the MVola API
Author-email: ryuka <lovanirina.ran@gmail.com>
License-File: LICENSE
Classifier: License :: OSI Approved :: MIT License
Classifier: Operating System :: OS Independent
Classifier: Programming Language :: Python :: 3
Requires-Python: >=3.7
Requires-Dist: requests
